logcatdevices/README.MD
logcatdevices/__init__.py
logcatdevices/requirements.txt
logcatdevices/thirdparty.json
logcatdevices-0.11.dist-info/LICENSE.rst
logcatdevices-0.11.dist-info/METADATA
logcatdevices-0.11.dist-info/WHEEL
logcatdevices-0.11.dist-info/top_level.txt
logcatdevices-0.11.dist-info/RECORD
