Metadata-Version: 2.1
Name: logcatdevices
Version: 0.11
Summary: Multiple ADB logcat with colored output / csv export
Home-page: https://github.com/hansalemaos/logcatdevices
Author: Johannes Fischer
Author-email: aulasparticularesdealemaosp@gmail.com
License: MIT
Keywords: adb,connect,logcat
Classifier: Development Status :: 4 - Beta
Classifier: Programming Language :: Python :: 3 :: Only
Classifier: Programming Language :: Python :: 3.10
Classifier: Topic :: Software Development :: Libraries :: Python Modules
Classifier: Topic :: Utilities
License-File: LICENSE.rst
Requires-Dist: ansi
Requires-Dist: kthread
Requires-Dist: kthread-sleep
Requires-Dist: shortpath83
Requires-Dist: touchtouch
Requires-Dist: what-os
